RKPairip/Anti_Splits.py
RKPairip/CRC.py
RKPairip/C_M.py
RKPairip/Decompile_Compile.py
RKPairip/Delete_Smali.py
RKPairip/Extract.py
RKPairip/Files_Check.py
RKPairip/Fix_Dex.py
RKPairip/Instruction_Credit.py
RKPairip/Logs_Inject.py
RKPairip/Manifest_Patch.py
RKPairip/Other_Patch.py
RKPairip/RK_Pairip.py
RKPairip/Smali_Patch.py
RKPairip/__init__.py
RKPairip/__main__.py
RKPairip/scan.py
RK_Pairip-1.0.dist-info/LICENSE
RK_Pairip-1.0.dist-info/METADATA
RK_Pairip-1.0.dist-info/WHEEL
RK_Pairip-1.0.dist-info/entry_points.txt
RK_Pairip-1.0.dist-info/top_level.txt
RK_Pairip-1.0.dist-info/RECORD
